tamarai/__init__.py
tamarai/code_a.py
tamarai/code_b.py
tamarai-6.6.6.dist-info/LICENSE.txt
tamarai-6.6.6.dist-info/METADATA
tamarai-6.6.6.dist-info/WHEEL
tamarai-6.6.6.dist-info/top_level.txt
tamarai-6.6.6.dist-info/RECORD
