Metadata-Version: 2.1
Name: tamarai
Version: 6.6.6
Summary: a small package made for learning how to make a package
Home-page: https://github.com/boypig24/tamarai
Author: Roy Attias
Author-email: roy.attias@outlook.com
License: UNKNOWN
Platform: UNKNOWN
Classifier: Programming Language :: Python :: 3
Classifier: License :: OSI Approved :: MIT License
Classifier: Operating System :: OS Independent
